openocr/__init__.py
openocr/api.py
openocr/check_file.py
openocr/openocr_det.py
openocr/openocr_e2e.py
openocr/openocr_rec.py
openocr/operators.py
openocr/test_det.py
openocr/test_e2e.py
openocr/test_rec.py
openocr/utility.py
openocr/data/__init__.py
openocr/data/operators.py
openocr/doc/ppocr_keys_v1.txt
openocr/postprocess/__init__.py
openocr/postprocess/det_postprocess.py
openocr/postprocess/rec_postprocess.py
openocr_python-0.2.3.dist-info/LICENSE
openocr_python-0.2.3.dist-info/METADATA
openocr_python-0.2.3.dist-info/WHEEL
openocr_python-0.2.3.dist-info/top_level.txt
openocr_python-0.2.3.dist-info/RECORD
