Metadata-Version: 2.1
Name: openocr-python
Version: 0.2.3
Summary: a python package for openocr, which is used to help developers quickly deploy OCR algorithms implemented in the openocr framework.
Home-page: https://github.com/Topdu/OpenOCR
Author: OpenOCR
Author-email: 18300180089@fudan.edu.cn
Project-URL: Source Code, https://github.com/Topdu/OpenOCR
Keywords: python,OCR,STR,OpenOCR,openocr
Classifier: Development Status :: 1 - Planning
Classifier: Intended Audience :: Developers
Classifier: Programming Language :: Python :: 3
Classifier: Operating System :: Unix
Classifier: Operating System :: Microsoft :: Windows
License-File: LICENSE
Requires-Dist: numpy
Requires-Dist: opencv-python (<=4.6.0.66)
Requires-Dist: pyclipper
